bioagent/__about__.py
bioagent/__init__.py
bioagent-0.0.0.dist-info/LICENSE
bioagent-0.0.0.dist-info/METADATA
bioagent-0.0.0.dist-info/WHEEL
bioagent-0.0.0.dist-info/top_level.txt
bioagent-0.0.0.dist-info/RECORD
